README.md
setup.cfg
setup.py
tensorflowonspark/TFCluster.py
tensorflowonspark/TFManager.py
tensorflowonspark/TFNode.py
tensorflowonspark/TFSparkNode.py
tensorflowonspark/__init__.py
tensorflowonspark/dfutil.py
tensorflowonspark/gpu_info.py
tensorflowonspark/marker.py
tensorflowonspark/pipeline.py
tensorflowonspark/reservation.py
tensorflowonspark/reservation_client.py
tensorflowonspark/util.py
test/test.py
test/test_TFCluster.py
test/test_TFNode.py
test/test_dfutil.py
test/test_pipeline.py
test/test_reservation.py
tfspark.egg-info/PKG-INFO
tfspark.egg-info/SOURCES.txt
tfspark.egg-info/dependency_links.txt
tfspark.egg-info/top_level.txt