Metadata-Version: 1.1
Name: tfspark
Version: 0.0.0.1
Summary: Hops Hadoop version of TensorFlow on Spark (not for Apache Hadoop), leverages GPU scheduling
Home-page: https://github.com/hopshadoop/TensorFlowOnSpark
Author: Yahoo, Inc., Logical Clocks AB
Author-email: UNKNOWN
License: Apache 2.0
Keywords: tensorflowonspark,tensorflow,spark,machine learning,yahoo,hops
Platform: UNKNOWN
Classifier: Development Status :: 4 - Beta
Classifier: Intended Audience :: Developers
Classifier: Intended Audience :: Science/Research
Classifier: License :: OSI Approved :: Apache Software License
Classifier: Topic :: Software Development :: Libraries
Classifier: Programming Language :: Python :: 2
Classifier: Programming Language :: Python :: 2.7
